[
	{
		"key": "datr",
		"value": "fhT-ZtkkjPQ0voL6dvcAX_FX",
		"domain": "facebook.com",
		"path": "/",
		"hostOnly": false,
		"creation": "2024-10-26T03:35:25.414Z",
		"lastAccessed": "2024-10-26T03:35:25.417Z"
	},
	{
		"key": "sb",
		"value": "fhT-ZqFfhhPy8oCtH8tYU8dw",
		"domain": "facebook.com",
		"path": "/",
		"hostOnly": false,
		"creation": "2024-10-26T03:35:25.417Z",
		"lastAccessed": "2024-10-26T03:35:25.417Z"
	},
	{
		"key": "ps_l",
		"value": "1",
		"domain": "facebook.com",
		"path": "/",
		"hostOnly": false,
		"creation": "2024-10-26T03:35:25.417Z",
		"lastAccessed": "2024-10-26T03:35:25.417Z"
	},
	{
		"key": "ps_n",
		"value": "1",
		"domain": "facebook.com",
		"path": "/",
		"hostOnly": false,
		"creation": "2024-10-26T03:35:25.417Z",
		"lastAccessed": "2024-10-26T03:35:25.417Z"
	},
	{
		"key": "dpr",
		"value": "3.2983407974243164",
		"domain": "facebook.com",
		"path": "/",
		"hostOnly": false,
		"creation": "2024-10-26T03:35:25.417Z",
		"lastAccessed": "2024-10-26T03:35:25.417Z"
	},
	{
		"key": "vpd",
		"value": "v1%3B680x360x3",
		"domain": "facebook.com",
		"path": "/",
		"hostOnly": false,
		"creation": "2024-10-26T03:35:25.417Z",
		"lastAccessed": "2024-10-26T03:35:25.417Z"
	},
	{
		"key": "locale",
		"value": "en_GB",
		"domain": "facebook.com",
		"path": "/",
		"hostOnly": false,
		"creation": "2024-10-26T03:35:25.417Z",
		"lastAccessed": "2024-10-26T03:35:25.417Z"
	},
	{
		"key": "m_pixel_ratio",
		"value": "3",
		"domain": "facebook.com",
		"path": "/",
		"hostOnly": false,
		"creation": "2024-10-26T03:35:25.417Z",
		"lastAccessed": "2024-10-26T03:35:25.417Z"
	},
	{
		"key": "c_user",
		"value": "61563240066217",
		"domain": "facebook.com",
		"path": "/",
		"hostOnly": false,
		"creation": "2024-10-26T03:35:25.417Z",
		"lastAccessed": "2024-10-26T03:35:25.417Z"
	},
	{
		"key": "fr",
		"value": "0eoYHMNmjXJ46TPWf.AWXydRpil-4Iv4pxq13HVBp5ywo.Bm_hR-..AAA.0.0.BnHGJH.AWUmOvrL69o",
		"domain": "facebook.com",
		"path": "/",
		"hostOnly": false,
		"creation": "2024-10-26T03:35:25.417Z",
		"lastAccessed": "2024-10-26T03:35:25.417Z"
	},
	{
		"key": "xs",
		"value": "35%3AyZFPYNWTYVZ5Og%3A2%3A1729913422%3A-1%3A5903",
		"domain": "facebook.com",
		"path": "/",
		"hostOnly": false,
		"creation": "2024-10-26T03:35:25.417Z",
		"lastAccessed": "2024-10-26T03:35:25.417Z"
	},
	{
		"key": "wd",
		"value": "360x680",
		"domain": "facebook.com",
		"path": "/",
		"hostOnly": false,
		"creation": "2024-10-26T03:35:25.417Z",
		"lastAccessed": "2024-10-26T03:35:25.417Z"
	},
	{
		"key": "fbl_st",
		"value": "100735608%3BT%3A28831891",
		"domain": "facebook.com",
		"path": "/",
		"hostOnly": false,
		"creation": "2024-10-26T03:35:25.417Z",
		"lastAccessed": "2024-10-26T03:35:25.417Z"
	},
	{
		"key": "wl_cbv",
		"value": "v2%3Bclient_version%3A2655%3Btimestamp%3A1729913469",
		"domain": "facebook.com",
		"path": "/",
		"hostOnly": false,
		"creation": "2024-10-26T03:35:25.417Z",
		"lastAccessed": "2024-10-26T03:35:25.417Z"
	}
]
